[
  {
    "id": "cm-campina-grande-luciano-breno-chaves-pereira-2025-01-28-0",
    "politicoId": "cm-campina-grande-luciano-breno-chaves-pereira",
    "data": "2025-01-28",
    "ano": 2025,
    "mes": 1,
    "categoria": "CONSULTORIA JURÍDICA",
    "fornecedor": {
      "nome": "BRUNO LIRA CARVALHO SOCIEDADE INDIVIDUAL DE ADVOCACIA",
      "cnpjCpf": "**.*28.764/000*-**"
    },
    "valor": 5000,
    "numeroNf": "19"
  },
  {
    "id": "cm-campina-grande-luciano-breno-chaves-pereira-2025-01-28-1",
    "politicoId": "cm-campina-grande-luciano-breno-chaves-pereira",
    "data": "2025-01-28",
    "ano": 2025,
    "mes": 1,
    "categoria": "ASSESSORIA CONTÁBIL",
    "fornecedor": {
      "nome": "SOUZA CONTABILIDADE LTDA",
      "cnpjCpf": "***.013.89*-**"
    },
    "valor": 2000,
    "numeroNf": "202"
  },
  {
    "id": "cm-campina-grande-luciano-breno-chaves-pereira-2025-01-02-2",
    "politicoId": "cm-campina-grande-luciano-breno-chaves-pereira",
    "data": "2025-01-02",
    "ano": 2025,
    "mes": 1,
    "categoria": "LOCAÇÃO",
    "fornecedor": {
      "nome": "JACICLEIDE SOARES DE OLIVEIRA NASCIMENTO",
      "cnpjCpf": "**.*47.279/000*-**"
    },
    "valor": 3000
  },
  {
    "id": "cm-campina-grande-luciano-breno-chaves-pereira-2025-02-26-3",
    "politicoId": "cm-campina-grande-luciano-breno-chaves-pereira",
    "data": "2025-02-26",
    "ano": 2025,
    "mes": 2,
    "categoria": "CONSULTORIA JURÍDICA",
    "fornecedor": {
      "nome": "BRUNO LIRA CARVALHO SOCIEDADE INDIVIDUAL DE ADVOCACIA",
      "cnpjCpf": "**.*28.764/000*-**"
    },
    "valor": 6000,
    "numeroNf": "24"
  },
  {
    "id": "cm-campina-grande-luciano-breno-chaves-pereira-2025-02-25-4",
    "politicoId": "cm-campina-grande-luciano-breno-chaves-pereira",
    "data": "2025-02-25",
    "ano": 2025,
    "mes": 2,
    "categoria": "ASSESSORIA CONTÁBIL",
    "fornecedor": {
      "nome": "SOUZA CONTABILIDADE LTDA",
      "cnpjCpf": "***.013.89*-**"
    },
    "valor": 4000,
    "numeroNf": "209"
  },
  {
    "id": "cm-campina-grande-luciano-breno-chaves-pereira-2025-02-01-5",
    "politicoId": "cm-campina-grande-luciano-breno-chaves-pereira",
    "data": "2025-02-01",
    "ano": 2025,
    "mes": 2,
    "categoria": "LOCAÇÃO",
    "fornecedor": {
      "nome": "JACICLEIDE SOARES DE OLIVEIRA NASCIMENTO",
      "cnpjCpf": "**.*47.279/000*-**"
    },
    "valor": 3000
  },
  {
    "id": "cm-campina-grande-luciano-breno-chaves-pereira-2025-02-26-6",
    "politicoId": "cm-campina-grande-luciano-breno-chaves-pereira",
    "data": "2025-02-26",
    "ano": 2025,
    "mes": 2,
    "categoria": "DIVULGAÇÃO",
    "fornecedor": {
      "nome": "FALA PREFEITO ASSESSORIA E MARKETING",
      "cnpjCpf": "**.*47.279/000*-**"
    },
    "valor": 4000,
    "numeroNf": "33"
  },
  {
    "id": "cm-campina-grande-luciano-breno-chaves-pereira-2025-03-26-7",
    "politicoId": "cm-campina-grande-luciano-breno-chaves-pereira",
    "data": "2025-03-26",
    "ano": 2025,
    "mes": 3,
    "categoria": "CONSULTORIA JURÍDICA",
    "fornecedor": {
      "nome": "BRUNO LIRA CARVALHO SOCIEDADE INDIVIDUAL DE ADVOCACIA",
      "cnpjCpf": "**.*28.764/000*-**"
    },
    "valor": 6000,
    "numeroNf": "26"
  },
  {
    "id": "cm-campina-grande-luciano-breno-chaves-pereira-2025-03-26-8",
    "politicoId": "cm-campina-grande-luciano-breno-chaves-pereira",
    "data": "2025-03-26",
    "ano": 2025,
    "mes": 3,
    "categoria": "ASSESSORIA CONTÁBIL",
    "fornecedor": {
      "nome": "SOUZA CONTABILIDADE LTDA",
      "cnpjCpf": "***.013.89*-**"
    },
    "valor": 4000,
    "numeroNf": "222"
  },
  {
    "id": "cm-campina-grande-luciano-breno-chaves-pereira-2025-03-01-9",
    "politicoId": "cm-campina-grande-luciano-breno-chaves-pereira",
    "data": "2025-03-01",
    "ano": 2025,
    "mes": 3,
    "categoria": "LOCAÇÃO",
    "fornecedor": {
      "nome": "JACICLEIDE SOARES DE OLIVEIRA NASCIMENTO",
      "cnpjCpf": "***.013.894-**"
    },
    "valor": 3000,
    "numeroNf": "CONTRATO"
  },
  {
    "id": "cm-campina-grande-luciano-breno-chaves-pereira-2025-03-27-10",
    "politicoId": "cm-campina-grande-luciano-breno-chaves-pereira",
    "data": "2025-03-27",
    "ano": 2025,
    "mes": 3,
    "categoria": "DIVULGAÇÃO",
    "fornecedor": {
      "nome": "FALA PREFEITO ASSESSORIA E MARKETING",
      "cnpjCpf": "**.*47.279/000*-**"
    },
    "valor": 4000,
    "numeroNf": "56"
  },
  {
    "id": "cm-campina-grande-luciano-breno-chaves-pereira-2025-04-28-11",
    "politicoId": "cm-campina-grande-luciano-breno-chaves-pereira",
    "data": "2025-04-28",
    "ano": 2025,
    "mes": 4,
    "categoria": "CONSULTORIA JURÍDICA",
    "fornecedor": {
      "nome": "BRUNO LIRA CARVALHO SOCIEDADE INDIVIDUAL DE ADVOCACIA",
      "cnpjCpf": "**.*28.764/000*-**"
    },
    "valor": 6000,
    "numeroNf": "49"
  },
  {
    "id": "cm-campina-grande-luciano-breno-chaves-pereira-2025-04-28-12",
    "politicoId": "cm-campina-grande-luciano-breno-chaves-pereira",
    "data": "2025-04-28",
    "ano": 2025,
    "mes": 4,
    "categoria": "ASSESSORIA CONTÁBIL",
    "fornecedor": {
      "nome": "SOUZA CONTABILIDADE LTDA",
      "cnpjCpf": "***.013.89*-**"
    },
    "valor": 2500,
    "numeroNf": "232"
  },
  {
    "id": "cm-campina-grande-luciano-breno-chaves-pereira-2025-04-01-13",
    "politicoId": "cm-campina-grande-luciano-breno-chaves-pereira",
    "data": "2025-04-01",
    "ano": 2025,
    "mes": 4,
    "categoria": "LOCAÇÃO",
    "fornecedor": {
      "nome": "JACICLEIDE SOARES DE OLIVEIRA NASCIMENTO",
      "cnpjCpf": "***.013.894-**"
    },
    "valor": 3000,
    "numeroNf": "CONTRATO"
  },
  {
    "id": "cm-campina-grande-luciano-breno-chaves-pereira-2025-04-28-14",
    "politicoId": "cm-campina-grande-luciano-breno-chaves-pereira",
    "data": "2025-04-28",
    "ano": 2025,
    "mes": 4,
    "categoria": "DIVULGAÇÃO",
    "fornecedor": {
      "nome": "FALA PREFEITO ASSESSORIA E MARKETING",
      "cnpjCpf": "**.*47.279/000*-**"
    },
    "valor": 3000,
    "numeroNf": "79"
  },
  {
    "id": "cm-campina-grande-luciano-breno-chaves-pereira-2025-04-28-15",
    "politicoId": "cm-campina-grande-luciano-breno-chaves-pereira",
    "data": "2025-04-28",
    "ano": 2025,
    "mes": 4,
    "categoria": "COMBUSTÍVEL",
    "fornecedor": {
      "nome": "AUTO POSTO JE COMBUSTÍVEIS LTDA",
      "cnpjCpf": "**.*76.998/000*-**"
    },
    "valor": 2464.07,
    "numeroNf": "556"
  },
  {
    "id": "cm-campina-grande-luciano-breno-chaves-pereira-2025-06-25-16",
    "politicoId": "cm-campina-grande-luciano-breno-chaves-pereira",
    "data": "2025-06-25",
    "ano": 2025,
    "mes": 6,
    "categoria": "CONSULTORIA JURÍDICA",
    "fornecedor": {
      "nome": "BRUNO LIRA CARVALHO SOCIEDADE INDIVIDUAL DE ADVOCACIA",
      "cnpjCpf": "**.*28.764/000*-**"
    },
    "valor": 6000,
    "numeroNf": "67"
  },
  {
    "id": "cm-campina-grande-luciano-breno-chaves-pereira-2025-06-01-17",
    "politicoId": "cm-campina-grande-luciano-breno-chaves-pereira",
    "data": "2025-06-01",
    "ano": 2025,
    "mes": 6,
    "categoria": "LOCAÇÃO",
    "fornecedor": {
      "nome": "JACICLEIDE SOARES DE OLIVEIRA NASCIMENTO",
      "cnpjCpf": "***.013.894-**"
    },
    "valor": 3000,
    "numeroNf": "CONTRATO"
  },
  {
    "id": "cm-campina-grande-luciano-breno-chaves-pereira-2025-06-25-18",
    "politicoId": "cm-campina-grande-luciano-breno-chaves-pereira",
    "data": "2025-06-25",
    "ano": 2025,
    "mes": 6,
    "categoria": "DIVULGAÇÃO",
    "fornecedor": {
      "nome": "FALA PREFEITO ASSESSORIA E MARKETING",
      "cnpjCpf": "**.*47.279/000*-**"
    },
    "valor": 4000,
    "numeroNf": "117"
  },
  {
    "id": "cm-campina-grande-luciano-breno-chaves-pereira-2025-06-25-19",
    "politicoId": "cm-campina-grande-luciano-breno-chaves-pereira",
    "data": "2025-06-25",
    "ano": 2025,
    "mes": 6,
    "categoria": "COMBUSTÍVEL",
    "fornecedor": {
      "nome": "AUTO POSTO JE COMBUSTÍVEIS LTDA",
      "cnpjCpf": "**.*76.998/000*-**"
    },
    "valor": 3838.75,
    "numeroNf": "598"
  },
  {
    "id": "cm-campina-grande-luciano-breno-chaves-pereira-2025-07-23-20",
    "politicoId": "cm-campina-grande-luciano-breno-chaves-pereira",
    "data": "2025-07-23",
    "ano": 2025,
    "mes": 7,
    "categoria": "CONSULTORIA JURÍDICA",
    "fornecedor": {
      "nome": "BRUNO LIRA CARVALHO SOCIEDADE INDIVIDUAL DE ADVOCACIA",
      "cnpjCpf": "**.*28.764/000*-**"
    },
    "valor": 6000,
    "numeroNf": "77"
  },
  {
    "id": "cm-campina-grande-luciano-breno-chaves-pereira-2025-07-01-21",
    "politicoId": "cm-campina-grande-luciano-breno-chaves-pereira",
    "data": "2025-07-01",
    "ano": 2025,
    "mes": 7,
    "categoria": "LOCAÇÃO",
    "fornecedor": {
      "nome": "JACICLEIDE SOARES DE OLIVEIRA NASCIMENTO",
      "cnpjCpf": "***.013.894-**"
    },
    "valor": 3000,
    "numeroNf": "CONTRATO"
  },
  {
    "id": "cm-campina-grande-luciano-breno-chaves-pereira-2025-07-25-22",
    "politicoId": "cm-campina-grande-luciano-breno-chaves-pereira",
    "data": "2025-07-25",
    "ano": 2025,
    "mes": 7,
    "categoria": "DIVULGAÇÃO",
    "fornecedor": {
      "nome": "FALA PREFEITO ASSESSORIA E MARKETING",
      "cnpjCpf": "**.*47.279/000*-**"
    },
    "valor": 5200,
    "numeroNf": "142"
  },
  {
    "id": "cm-campina-grande-luciano-breno-chaves-pereira-2025-07-24-23",
    "politicoId": "cm-campina-grande-luciano-breno-chaves-pereira",
    "data": "2025-07-24",
    "ano": 2025,
    "mes": 7,
    "categoria": "COMBUSTÍVEL",
    "fornecedor": {
      "nome": "AUTO POSTO JE COMBUSTÍVEIS LTDA",
      "cnpjCpf": "**.*76.998/000*-**"
    },
    "valor": 2768.66,
    "numeroNf": "619"
  },
  {
    "id": "cm-campina-grande-luciano-breno-chaves-pereira-2025-08-26-24",
    "politicoId": "cm-campina-grande-luciano-breno-chaves-pereira",
    "data": "2025-08-26",
    "ano": 2025,
    "mes": 8,
    "categoria": "CONSULTORIA JURÍDICA",
    "fornecedor": {
      "nome": "BRUNO LIRA CARVALHO SOCIEDADE INDIVIDUAL DE ADVOCACIA",
      "cnpjCpf": "**.*28.764/000*-**"
    },
    "valor": 6000,
    "numeroNf": "86"
  },
  {
    "id": "cm-campina-grande-luciano-breno-chaves-pereira-2025-08-01-25",
    "politicoId": "cm-campina-grande-luciano-breno-chaves-pereira",
    "data": "2025-08-01",
    "ano": 2025,
    "mes": 8,
    "categoria": "LOCAÇÃO",
    "fornecedor": {
      "nome": "JACICLEIDE SOARES DE OLIVEIRA NASCIMENTO",
      "cnpjCpf": "***.013.894-**"
    },
    "valor": 3000,
    "numeroNf": "CONTRATO"
  },
  {
    "id": "cm-campina-grande-luciano-breno-chaves-pereira-2025-08-26-26",
    "politicoId": "cm-campina-grande-luciano-breno-chaves-pereira",
    "data": "2025-08-26",
    "ano": 2025,
    "mes": 8,
    "categoria": "DIVULGAÇÃO",
    "fornecedor": {
      "nome": "FALA PREFEITO ASSESSORIA E MARKETING",
      "cnpjCpf": "**.*47.279/000*-**"
    },
    "valor": 5200,
    "numeroNf": "159"
  },
  {
    "id": "cm-campina-grande-luciano-breno-chaves-pereira-2025-08-25-27",
    "politicoId": "cm-campina-grande-luciano-breno-chaves-pereira",
    "data": "2025-08-25",
    "ano": 2025,
    "mes": 8,
    "categoria": "COMBUSTÍVEL",
    "fornecedor": {
      "nome": "AUTO POSTO JE COMBUSTÍVEIS LTDA",
      "cnpjCpf": "**.*76.998/000*-**"
    },
    "valor": 2285.01,
    "numeroNf": "640"
  },
  {
    "id": "cm-campina-grande-luciano-breno-chaves-pereira-2025-09-23-28",
    "politicoId": "cm-campina-grande-luciano-breno-chaves-pereira",
    "data": "2025-09-23",
    "ano": 2025,
    "mes": 9,
    "categoria": "CONSULTORIA JURÍDICA",
    "fornecedor": {
      "nome": "BRUNO LIRA CARVALHO SOCIEDADE INDIVIDUAL DE ADVOCACIA",
      "cnpjCpf": "**.*28.764/000*-**"
    },
    "valor": 6000,
    "numeroNf": "93"
  },
  {
    "id": "cm-campina-grande-luciano-breno-chaves-pereira-2025-09-01-29",
    "politicoId": "cm-campina-grande-luciano-breno-chaves-pereira",
    "data": "2025-09-01",
    "ano": 2025,
    "mes": 9,
    "categoria": "LOCAÇÃO",
    "fornecedor": {
      "nome": "JACICLEIDE SOARES DE OLIVEIRA NASCIMENTO",
      "cnpjCpf": "***.013.894-**"
    },
    "valor": 3000,
    "numeroNf": "CONTRATO"
  },
  {
    "id": "cm-campina-grande-luciano-breno-chaves-pereira-2025-09-23-30",
    "politicoId": "cm-campina-grande-luciano-breno-chaves-pereira",
    "data": "2025-09-23",
    "ano": 2025,
    "mes": 9,
    "categoria": "DIVULGAÇÃO",
    "fornecedor": {
      "nome": "FALA PREFEITO ASSESSORIA E MARKETING",
      "cnpjCpf": "**.*47.279/000*-**"
    },
    "valor": 5200,
    "numeroNf": "180"
  },
  {
    "id": "cm-campina-grande-luciano-breno-chaves-pereira-2025-09-24-31",
    "politicoId": "cm-campina-grande-luciano-breno-chaves-pereira",
    "data": "2025-09-24",
    "ano": 2025,
    "mes": 9,
    "categoria": "COMBUSTÍVEL",
    "fornecedor": {
      "nome": "AUTO POSTO JE COMBUSTÍVEIS LTDA",
      "cnpjCpf": "**.*76.998/000*-**"
    },
    "valor": 2644.77,
    "numeroNf": "669"
  },
  {
    "id": "cm-campina-grande-luciano-breno-chaves-pereira-2025-10-23-32",
    "politicoId": "cm-campina-grande-luciano-breno-chaves-pereira",
    "data": "2025-10-23",
    "ano": 2025,
    "mes": 10,
    "categoria": "CONSULTORIA JURÍDICA",
    "fornecedor": {
      "nome": "BRUNO LIRA CARVALHO SOCIEDADE INDIVIDUAL DE ADVOCACIA",
      "cnpjCpf": "**.*28.764/000*-**"
    },
    "valor": 6000,
    "numeroNf": "101"
  },
  {
    "id": "cm-campina-grande-luciano-breno-chaves-pereira-2025-10-01-33",
    "politicoId": "cm-campina-grande-luciano-breno-chaves-pereira",
    "data": "2025-10-01",
    "ano": 2025,
    "mes": 10,
    "categoria": "LOCAÇÃO",
    "fornecedor": {
      "nome": "JACICLEIDE SOARES DE OLIVEIRA NASCIMENTO",
      "cnpjCpf": "***.013.894-**"
    },
    "valor": 3000,
    "numeroNf": "CONTRATO"
  },
  {
    "id": "cm-campina-grande-luciano-breno-chaves-pereira-2025-10-23-34",
    "politicoId": "cm-campina-grande-luciano-breno-chaves-pereira",
    "data": "2025-10-23",
    "ano": 2025,
    "mes": 10,
    "categoria": "DIVULGAÇÃO",
    "fornecedor": {
      "nome": "FALA PREFEITO ASSESSORIA E MARKETING",
      "cnpjCpf": "**.*47.279/000*-**"
    },
    "valor": 5200,
    "numeroNf": "202"
  },
  {
    "id": "cm-campina-grande-luciano-breno-chaves-pereira-2025-10-23-35",
    "politicoId": "cm-campina-grande-luciano-breno-chaves-pereira",
    "data": "2025-10-23",
    "ano": 2025,
    "mes": 10,
    "categoria": "COMBUSTÍVEL",
    "fornecedor": {
      "nome": "AUTO POSTO JE COMBUSTÍVEIS LTDA",
      "cnpjCpf": "**.*76.998/000*-**"
    },
    "valor": 2967.4,
    "numeroNf": "692"
  },
  {
    "id": "cm-campina-grande-luciano-breno-chaves-pereira-2025-11-24-36",
    "politicoId": "cm-campina-grande-luciano-breno-chaves-pereira",
    "data": "2025-11-24",
    "ano": 2025,
    "mes": 11,
    "categoria": "CONSULTORIA JURÍDICA",
    "fornecedor": {
      "nome": "BRUNO LIRA CARVALHO SOCIEDADE INDIVIDUAL DE ADVOCACIA",
      "cnpjCpf": "**.*28.764/000*-**"
    },
    "valor": 6000,
    "numeroNf": "110"
  },
  {
    "id": "cm-campina-grande-luciano-breno-chaves-pereira-2025-11-24-37",
    "politicoId": "cm-campina-grande-luciano-breno-chaves-pereira",
    "data": "2025-11-24",
    "ano": 2025,
    "mes": 11,
    "categoria": "LOCAÇÃO",
    "fornecedor": {
      "nome": "JANICLEIDE SOARES DE OLIVEIRA NASCIMENTO",
      "cnpjCpf": "***.013.894-**"
    },
    "valor": 3000,
    "numeroNf": "CONTRATO"
  },
  {
    "id": "cm-campina-grande-luciano-breno-chaves-pereira-2025-11-24-38",
    "politicoId": "cm-campina-grande-luciano-breno-chaves-pereira",
    "data": "2025-11-24",
    "ano": 2025,
    "mes": 11,
    "categoria": "DIVULGAÇÃO",
    "fornecedor": {
      "nome": "FALA PREFEITO ASSESSORIA E MARKETING",
      "cnpjCpf": "**.*47.279/000*-**"
    },
    "valor": 5200,
    "numeroNf": "228"
  },
  {
    "id": "cm-campina-grande-luciano-breno-chaves-pereira-2025-11-26-39",
    "politicoId": "cm-campina-grande-luciano-breno-chaves-pereira",
    "data": "2025-11-26",
    "ano": 2025,
    "mes": 11,
    "categoria": "COMBUSTÍVEL",
    "fornecedor": {
      "nome": "AUTO POSTO JE COMBUSTÍVEIS LTDA",
      "cnpjCpf": "**.*76.998/000*-**"
    },
    "valor": 2748.18,
    "numeroNf": "715"
  },
  {
    "id": "cm-campina-grande-luciano-breno-chaves-pereira-2025-12-18-40",
    "politicoId": "cm-campina-grande-luciano-breno-chaves-pereira",
    "data": "2025-12-18",
    "ano": 2025,
    "mes": 12,
    "categoria": "CONSULTORIA JURÍDICA",
    "fornecedor": {
      "nome": "BRUNO LIRA CARVALHO SOCIEDADE INDIVIDUAL DE ADVOCACIA",
      "cnpjCpf": "**.*28.764/000*-**"
    },
    "valor": 6000,
    "numeroNf": "114"
  },
  {
    "id": "cm-campina-grande-luciano-breno-chaves-pereira-2025-12-18-41",
    "politicoId": "cm-campina-grande-luciano-breno-chaves-pereira",
    "data": "2025-12-18",
    "ano": 2025,
    "mes": 12,
    "categoria": "LOCAÇÃO",
    "fornecedor": {
      "nome": "JANICLEIDE SOARES DE OLIVEIRA NASCIMENTO",
      "cnpjCpf": "***.013.894-**"
    },
    "valor": 3000,
    "numeroNf": "CONTRATO"
  },
  {
    "id": "cm-campina-grande-luciano-breno-chaves-pereira-2025-12-18-42",
    "politicoId": "cm-campina-grande-luciano-breno-chaves-pereira",
    "data": "2025-12-18",
    "ano": 2025,
    "mes": 12,
    "categoria": "DIVULGAÇÃO",
    "fornecedor": {
      "nome": "FALA PREFEITO ASSESSORIA E MARKETING",
      "cnpjCpf": "**.*47.279/000*-**"
    },
    "valor": 5200,
    "numeroNf": "249"
  },
  {
    "id": "cm-campina-grande-luciano-breno-chaves-pereira-2025-12-18-43",
    "politicoId": "cm-campina-grande-luciano-breno-chaves-pereira",
    "data": "2025-12-18",
    "ano": 2025,
    "mes": 12,
    "categoria": "COMBUSTÍVEL",
    "fornecedor": {
      "nome": "AUTO POSTO JE COMBUSTÍVEIS LTDA",
      "cnpjCpf": "**.*76.998/000*-**"
    },
    "valor": 2750.08,
    "numeroNf": "742"
  },
  {
    "id": "cm-campina-grande-luciano-breno-chaves-pereira-2026-01-26-44",
    "politicoId": "cm-campina-grande-luciano-breno-chaves-pereira",
    "data": "2026-01-26",
    "ano": 2026,
    "mes": 1,
    "categoria": "CONSULTORIA JURÍDICA",
    "fornecedor": {
      "nome": "BRUNO LIRA CARVALHO SOCIEDADE INDIVIDUAL DE ADVOCACIA",
      "cnpjCpf": "**.*28.764/000*-**"
    },
    "valor": 6000,
    "numeroNf": "125"
  },
  {
    "id": "cm-campina-grande-luciano-breno-chaves-pereira-2026-01-26-45",
    "politicoId": "cm-campina-grande-luciano-breno-chaves-pereira",
    "data": "2026-01-26",
    "ano": 2026,
    "mes": 1,
    "categoria": "DIVULGAÇÃO",
    "fornecedor": {
      "nome": "FALA PREFEITO ASSESSORIA E MARETING",
      "cnpjCpf": "**.*47.297/000*-**"
    },
    "valor": 3000,
    "numeroNf": "17"
  },
  {
    "id": "cm-campina-grande-luciano-breno-chaves-pereira-2026-01-22-46",
    "politicoId": "cm-campina-grande-luciano-breno-chaves-pereira",
    "data": "2026-01-22",
    "ano": 2026,
    "mes": 1,
    "categoria": "LOCAÇÃO",
    "fornecedor": {
      "nome": "JACICLEIDE SOARES DE OLIVEIRA NASCIMENTO",
      "cnpjCpf": "**.*47.279/000*-**"
    },
    "valor": 3000,
    "numeroNf": "CONTRATO"
  }
]