[
  {
    "id": "alesc-joao-amin-2023-01-1",
    "politicoId": "alesc-joao-amin",
    "data": "2023-01-31",
    "ano": 2023,
    "mes": 1,
    "categoria": "ASSINATURA DE TV A CABO",
    "fornecedor": {
      "nome": ""
    },
    "valor": 115.55
  },
  {
    "id": "alesc-joao-amin-2023-01-2",
    "politicoId": "alesc-joao-amin",
    "data": "2023-01-17",
    "ano": 2023,
    "mes": 1,
    "categoria": "TELEFONE",
    "fornecedor": {
      "nome": ""
    },
    "valor": 15.2
  },
  {
    "id": "alesc-joao-amin-2023-01-3",
    "politicoId": "alesc-joao-amin",
    "data": "2023-01-31",
    "ano": 2023,
    "mes": 1,
    "categoria": "TELEFONE",
    "fornecedor": {
      "nome": ""
    },
    "valor": 40.73
  },
  {
    "id": "alesc-joao-amin-2023-01-4",
    "politicoId": "alesc-joao-amin",
    "data": "2023-01-31",
    "ano": 2023,
    "mes": 1,
    "categoria": "VEÍCULOS",
    "fornecedor": {
      "nome": ""
    },
    "valor": 8663.73
  }
]